pytest_aio/__init__.py
pytest_aio/plugin.py
pytest_aio/py.typed
pytest_aio/runners.py
pytest_aio/utils.py
pytest_aio-2.0.0.dist-info/METADATA
pytest_aio-2.0.0.dist-info/WHEEL
pytest_aio-2.0.0.dist-info/entry_points.txt
pytest_aio-2.0.0.dist-info/RECORD
