Metadata-Version: 2.4
Name: pytest-aio
Version: 2.0.0
Summary: Pytest plugin for testing async python code
License: MIT
Keywords: pytest,asyncio,trio,curio
Author: Kirill Klenov
Author-email: horneds@gmail.com
Requires-Python: >=3.10,<4.0
Classifier: Development Status :: 5 - Production/Stable
Classifier: Framework :: Pytest
Classifier: Intended Audience :: Developers
Classifier: License :: OSI Approved :: MIT License
Classifier: Programming Language :: Python
Classifier: Programming Language :: Python :: 3
Classifier: Programming Language :: Python :: 3.10
Classifier: Programming Language :: Python :: 3.11
Classifier: Programming Language :: Python :: 3.12
Classifier: Programming Language :: Python :: 3.13
Classifier: Programming Language :: Python :: 3.14
Classifier: Programming Language :: Python :: Implementation :: PyPy
Classifier: Topic :: Software Development :: Testing
Provides-Extra: curio
Provides-Extra: trio
Provides-Extra: uvloop
Requires-Dist: curio-compat ; extra == "curio"
Requires-Dist: pytest
Requires-Dist: trio ; extra == "trio"
Requires-Dist: uvloop ; extra == "uvloop"
Project-URL: Homepage, https://github.com/klen/pytest-aio
Project-URL: Repository, https://github.com/klen/pytest-aio
